{
  "id": 625444,
  "status": "FINAL",
  "original_status": "CONFLICT",
  "home_team": "CANAM BEAUCE-APPALACHES",
  "away_team": "ALBATROS",
  "date": "2026-02-08",
  "start_time": "2026-02-08T17:15:00.000Z",
  "home_score": 1,
  "away_score": 4,
  "game_type": "season",
  "schedule_id": 182366,
  "detail_url": "https://lheq.qc.ca/calendrier/625444",
  "gamesheet_pdf_url": "https://pdf.play.spordle.com/game/625444?locale=fr",
  "boxscore": {
    "gameNumber": "2105",
    "teams": [
      {
        "id": 128304,
        "name": "CANAM BEAUCE-APPALACHES",
        "isPublic": true,
        "logoUrl": "https://cdn.hcr.spordle.com/teams/1f05e5ce-41b4-690a-be7d-0627b38ad1df/logos/1f05e5ce-4194-6e3e-872e-0627b38ad1df.png"
      },
      {
        "id": 128312,
        "name": "ALBATROS",
        "isPublic": true,
        "logoUrl": "https://d1yykh3c16sa22.cloudfront.net/teams/1f05e5ce-433e-62f8-a08b-0627b38ad1df/logos/1f05e5ce-431f-6e66-9568-0627b38ad1df.jpg"
      }
    ],
    "goals": [
      {
        "gameTime": {
          "period": "3",
          "minutes": 3,
          "seconds": 27,
          "elapsedMinutes": 11,
          "elapsedSeconds": 33
        },
        "teamId": 128312,
        "participant": {
          "fullName": "HUBERT MORNEAU",
          "number": 47,
          "participantId": 955003,
          "pictureUrl": "https://cdn.hcr.spordle.com/members/1ebb64e1-c4c1-6ebe-9b63-020a2d3ab872/profile/small/1f0be441-5c32-6f9e-a85e-067f8c035ee7.jpg",
          "isAffiliate": false
        },
        "assists": [
          {
            "fullName": "ELIOTT WHITTOM",
            "number": 98,
            "participantId": 955008,
            "pictureUrl": "https://cdn.hcr.spordle.com/members/1ebb64ee-5a17-60f2-8176-021e976b8d94/profile/small/1f0be444-ce88-69ba-870a-067f8c035ee7.jpg",
            "isAffiliate": false
          }
        ],
        "isPowerplay": false,
        "isShorthanded": false,
        "isEmptyNet": false,
        "isPenaltyShot": false,
        "isOwnGoal": null
      },
      {
        "gameTime": {
          "period": "2",
          "minutes": 9,
          "seconds": 47,
          "elapsedMinutes": 5,
          "elapsedSeconds": 13
        },
        "teamId": 128312,
        "participant": {
          "fullName": "ELIOTT WHITTOM",
          "number": 98,
          "participantId": 955008,
          "pictureUrl": "https://cdn.hcr.spordle.com/members/1ebb64ee-5a17-60f2-8176-021e976b8d94/profile/small/1f0be444-ce88-69ba-870a-067f8c035ee7.jpg",
          "isAffiliate": false
        },
        "assists": [],
        "isPowerplay": true,
        "isShorthanded": false,
        "isEmptyNet": false,
        "isPenaltyShot": false,
        "isOwnGoal": null
      },
      {
        "gameTime": {
          "period": "2",
          "minutes": 2,
          "seconds": 52,
          "elapsedMinutes": 12,
          "elapsedSeconds": 8
        },
        "teamId": 128312,
        "participant": {
          "fullName": "LOGAN BLAIS",
          "number": 9,
          "participantId": 956002,
          "pictureUrl": "https://cdn.hcr.spordle.com/members/1ebb6591-dee5-6056-8ddf-06798f358960/profile/small/1f0be434-74e5-6292-969a-02ec0d6aa587.jpg",
          "isAffiliate": false
        },
        "assists": [
          {
            "fullName": "THÉO GAUTHIER",
            "number": 89,
            "participantId": 955002,
            "pictureUrl": "https://cdn.hcr.spordle.com/members/1ebb64e0-3796-67e8-b418-06803bcf766a/profile/small/1f0be43d-ab63-6c20-8d97-02ec0d6aa587.jpg",
            "isAffiliate": false
          }
        ],
        "isPowerplay": false,
        "isShorthanded": false,
        "isEmptyNet": false,
        "isPenaltyShot": false,
        "isOwnGoal": null
      },
      {
        "gameTime": {
          "period": "2",
          "minutes": 13,
          "seconds": 17,
          "elapsedMinutes": 1,
          "elapsedSeconds": 43
        },
        "teamId": 128304,
        "participant": {
          "fullName": "LOUIS DROUIN",
          "number": 26,
          "participantId": 957501,
          "pictureUrl": "https://cdn.hcr.spordle.com/members/1ebb653a-3e91-6fde-b57d-0695742fcc0e/profile/small/1f0b99dd-c39f-6be0-bafb-02ec0d6aa587.jpg",
          "isAffiliate": false
        },
        "assists": [
          {
            "fullName": "JUSTIN TANGUAY",
            "number": 40,
            "participantId": 957510,
            "pictureUrl": "https://cdn.hcr.spordle.com/members/1ebb653f-4c41-653a-9a95-021e976b8d94/profile/small/1f0b99e9-1fe9-6a94-bc84-02ec0d6aa587.jpg",
            "isAffiliate": false
          },
          {
            "fullName": "LOHAN BRUNEAU",
            "number": 35,
            "participantId": 795350,
            "pictureUrl": "https://cdn.hcr.spordle.com/members/1ebb653d-bf4f-642a-8f4b-068fc9a36a40/profile/small/1f0b99d5-bbe6-6b9a-bc3c-067f8c035ee7.jpg",
            "isAffiliate": false
          }
        ],
        "isPowerplay": false,
        "isShorthanded": false,
        "isEmptyNet": false,
        "isPenaltyShot": false,
        "isOwnGoal": null
      },
      {
        "gameTime": {
          "period": "2",
          "minutes": 12,
          "seconds": 35,
          "elapsedMinutes": 2,
          "elapsedSeconds": 25
        },
        "teamId": 128312,
        "participant": {
          "fullName": "LOUIS TREMBLAY",
          "number": 34,
          "participantId": 955001,
          "pictureUrl": "https://cdn.hcr.spordle.com/members/1ebb64e0-4192-6cce-a2d0-021e976b8d94/profile/small/1f0be443-d389-6a32-8fa6-02ec0d6aa587.jpg",
          "isAffiliate": false
        },
        "assists": [
          {
            "fullName": "FLORA-MAY CHOUINARD",
            "number": 29,
            "participantId": 955009,
            "pictureUrl": "https://cdn.hcr.spordle.com/members/1ec41712-7ac7-6282-b8f1-0200963e0a9c/profile/small/1f0be437-2a0f-6490-9ef6-02d85374e4dd.jpg",
            "isAffiliate": false
          }
        ],
        "isPowerplay": true,
        "isShorthanded": false,
        "isEmptyNet": false,
        "isPenaltyShot": false,
        "isOwnGoal": null
      }
    ],
    "shootout": [],
    "penalties": [
      {
        "gameTime": {
          "period": "1",
          "minutes": 4,
          "seconds": 52,
          "elapsedMinutes": 10,
          "elapsedSeconds": 8
        },
        "teamId": 128304,
        "infraction": "Tripping",
        "duration": {
          "name": "Minor",
          "description": null,
          "i18n": {
            "fr": {
              "name": "Mineure"
            }
          }
        },
        "participant": {
          "fullName": "DONOVAN LESSARD",
          "number": 47,
          "participantId": 957507,
          "pictureUrl": "https://cdn.hcr.spordle.com/members/1ebb653a-085d-6a62-b4c1-06803bcf766a/profile/small/1f0b99e2-e59c-6d06-8aa4-067f8c035ee7.jpg",
          "isAffiliate": false
        },
        "isBenchPenalty": false,
        "code": null,
        "i18n": {
          "fr": {
            "infraction": "Faire trébucher"
          }
        }
      },
      {
        "gameTime": {
          "period": "2",
          "minutes": 5,
          "seconds": 8,
          "elapsedMinutes": 9,
          "elapsedSeconds": 52
        },
        "teamId": 128312,
        "infraction": "Tripping",
        "duration": {
          "name": "Minor",
          "description": null,
          "i18n": {
            "fr": {
              "name": "Mineure"
            }
          }
        },
        "participant": {
          "fullName": "HUBERT MORNEAU",
          "number": 47,
          "participantId": 955003,
          "pictureUrl": "https://cdn.hcr.spordle.com/members/1ebb64e1-c4c1-6ebe-9b63-020a2d3ab872/profile/small/1f0be441-5c32-6f9e-a85e-067f8c035ee7.jpg",
          "isAffiliate": false
        },
        "isBenchPenalty": false,
        "code": null,
        "i18n": {
          "fr": {
            "infraction": "Faire trébucher"
          }
        }
      },
      {
        "gameTime": {
          "period": "2",
          "minutes": 12,
          "seconds": 52,
          "elapsedMinutes": 2,
          "elapsedSeconds": 8
        },
        "teamId": 128304,
        "infraction": "Holding",
        "duration": {
          "name": "Minor",
          "description": null,
          "i18n": {
            "fr": {
              "name": "Mineure"
            }
          }
        },
        "participant": {
          "fullName": "MILAN VACHON",
          "number": 41,
          "participantId": 957509,
          "pictureUrl": "https://cdn.hcr.spordle.com/members/1ebb653e-151d-6406-88a8-021e976b8d94/profile/small/1f0b99ea-3c24-6f46-bb35-02ec0d6aa587.jpg",
          "isAffiliate": false
        },
        "isBenchPenalty": false,
        "code": null,
        "i18n": {
          "fr": {
            "infraction": "Retenir"
          }
        }
      },
      {
        "gameTime": {
          "period": "1",
          "minutes": 13,
          "seconds": 13,
          "elapsedMinutes": 1,
          "elapsedSeconds": 47
        },
        "teamId": 128312,
        "infraction": "Tripping",
        "duration": {
          "name": "Minor",
          "description": null,
          "i18n": {
            "fr": {
              "name": "Mineure"
            }
          }
        },
        "participant": {
          "fullName": "LOÏC GRENIER",
          "number": 22,
          "participantId": 814079,
          "isAffiliate": false
        },
        "isBenchPenalty": false,
        "code": null,
        "i18n": {
          "fr": {
            "infraction": "Faire trébucher"
          }
        }
      },
      {
        "gameTime": {
          "period": "3",
          "minutes": 2,
          "seconds": 58,
          "elapsedMinutes": 12,
          "elapsedSeconds": 2
        },
        "teamId": 128312,
        "infraction": "Interference",
        "duration": {
          "name": "Minor",
          "description": null,
          "i18n": {
            "fr": {
              "name": "Mineure"
            }
          }
        },
        "participant": {
          "fullName": "LOGAN BLAIS",
          "number": 9,
          "participantId": 956002,
          "pictureUrl": "https://cdn.hcr.spordle.com/members/1ebb6591-dee5-6056-8ddf-06798f358960/profile/small/1f0be434-74e5-6292-969a-02ec0d6aa587.jpg",
          "isAffiliate": false
        },
        "isBenchPenalty": false,
        "code": null,
        "i18n": {
          "fr": {
            "infraction": "Obstruction"
          }
        }
      },
      {
        "gameTime": {
          "period": "3",
          "minutes": 7,
          "seconds": 48,
          "elapsedMinutes": 7,
          "elapsedSeconds": 12
        },
        "teamId": 128312,
        "infraction": "Holding",
        "duration": {
          "name": "Minor",
          "description": null,
          "i18n": {
            "fr": {
              "name": "Mineure"
            }
          }
        },
        "participant": {
          "fullName": "FELIX BOUCHARD",
          "number": 16,
          "participantId": 955013,
          "pictureUrl": "https://cdn.hcr.spordle.com/members/1ebb64e1-c29c-69e0-9cc0-0695742fcc0e/profile/small/1f0be435-75dc-68b6-8a0e-02d85374e4dd.jpg",
          "isAffiliate": false
        },
        "isBenchPenalty": false,
        "code": null,
        "i18n": {
          "fr": {
            "infraction": "Retenir"
          }
        }
      },
      {
        "gameTime": {
          "period": "1",
          "minutes": 1,
          "seconds": 41,
          "elapsedMinutes": 13,
          "elapsedSeconds": 19
        },
        "teamId": 128304,
        "infraction": "Interference",
        "duration": {
          "name": "Minor",
          "description": null,
          "i18n": {
            "fr": {
              "name": "Mineure"
            }
          }
        },
        "participant": {
          "fullName": "HUBERT CORRIVEAU",
          "number": 28,
          "participantId": 957505,
          "pictureUrl": "https://cdn.hcr.spordle.com/members/1ebb653f-b65c-6500-9488-020a2d3ab872/profile/small/1f0b99dc-a7ea-63f6-847d-067f8c035ee7.jpg",
          "isAffiliate": false
        },
        "isBenchPenalty": false,
        "code": null,
        "i18n": {
          "fr": {
            "infraction": "Obstruction"
          }
        }
      },
      {
        "gameTime": {
          "period": "2",
          "minutes": 10,
          "seconds": 47,
          "elapsedMinutes": 4,
          "elapsedSeconds": 13
        },
        "teamId": 128304,
        "infraction": "Interference",
        "duration": {
          "name": "Minor",
          "description": null,
          "i18n": {
            "fr": {
              "name": "Mineure"
            }
          }
        },
        "participant": {
          "fullName": "HUBERT BAILLARGEON",
          "number": 43,
          "participantId": 957506,
          "pictureUrl": "https://cdn.hcr.spordle.com/members/1ebb653c-4e32-607c-984f-0695742fcc0e/profile/small/1f0b99d2-59de-6536-8a6a-02d85374e4dd.jpg",
          "isAffiliate": false
        },
        "isBenchPenalty": false,
        "code": null,
        "i18n": {
          "fr": {
            "infraction": "Obstruction"
          }
        }
      }
    ]
  },
  "detailed_game_info": {
    "number": "2105",
    "date": "2026-02-08",
    "startTime": "2026-02-08T17:15:00.000Z",
    "endTime": "2026-02-08T18:45:00.000Z",
    "timezone": "America/Toronto",
    "division": "U13",
    "gender": "Integrated",
    "categoryId": "ba267b3e-9734-478c-a9e2-4890895cfc47",
    "seasonId": "2025-26",
    "arenaId": 10532,
    "scheduleId": 182366,
    "groupId": null,
    "crossGroupId": null,
    "crossScheduleId": null,
    "officeId": 9175,
    "homeTeamId": 128304,
    "awayTeamId": 128312,
    "homeTeamComment": null,
    "awayTeamComment": null,
    "homeTeamStats": true,
    "awayTeamStats": true,
    "status": "Conflict",
    "comments": null,
    "isApproved": true,
    "isCertified": true,
    "spectators": null,
    "actualStartTime": "2026-02-08T17:17:00.000Z",
    "actualEndTime": "2026-02-08T18:35:00.000Z",
    "id": 625444,
    "category": {
      "id": "ba267b3e-9734-478c-a9e2-4890895cfc47",
      "name": "U13 AAA Elite",
      "divisionId": "5904e905-ab85-4a34-85ac-9fcae9204250",
      "gender": "Integrated",
      "classId": "0b050ba5-ddd1-4759-9ad9-5ac1bf365ac7",
      "order": 1602,
      "i18n": {
        "fr": {
          "name": "M13 AAA Elite"
        }
      },
      "nameFr": "M13 AAA Elite",
      "externalId": "1f030d9f-9961-6798-8152-0666a1a64601",
      "division": {
        "id": "5904e905-ab85-4a34-85ac-9fcae9204250",
        "name": "U13",
        "shortName": "U13",
        "order": 10,
        "i18n": {
          "fr": {
            "name": "M13",
            "shortName": "M13"
          }
        }
      },
      "class": {
        "id": "0b050ba5-ddd1-4759-9ad9-5ac1bf365ac7",
        "name": "AAA",
        "shortName": "AAA",
        "order": 1,
        "i18n": {
          "fr": {
            "name": "AAA",
            "shortName": "AAA"
          }
        }
      }
    },
    "teamStats": [
      {
        "gameId": 625444,
        "teamId": 128312,
        "schemaId": "8f056ea1-457e-4fc6-b9f7-86e4e04eb058",
        "id": 1231505,
        "pk": 4,
        "pim": 8,
        "pko": 4,
        "ppg": 2,
        "ppo": 4,
        "points": 2,
        "goalFor": 4,
        "shotFor": null,
        "pointsPct": 1,
        "gameResult": "win",
        "goalAgainst": 1,
        "shotAgainst": null,
        "winLossType": "regulation",
        "sportsmanship": 1,
        "sportsmanshipPim": {
          "totalPim": 2,
          "regularTimePim": 2
        },
        "penaltyOccurrences": 4
      },
      {
        "gameId": 625444,
        "teamId": 128304,
        "schemaId": "8f056ea1-457e-4fc6-b9f7-86e4e04eb058",
        "id": 1231506,
        "pk": 2,
        "pim": 8,
        "pko": 4,
        "ppg": 0,
        "ppo": 4,
        "points": 0,
        "goalFor": 1,
        "shotFor": null,
        "pointsPct": 0.333,
        "gameResult": "loss",
        "goalAgainst": 4,
        "shotAgainst": null,
        "winLossType": "regulation",
        "sportsmanship": 1,
        "sportsmanshipPim": {
          "totalPim": 4,
          "regularTimePim": 4
        },
        "penaltyOccurrences": 4
      }
    ],
    "surface": {
      "venueId": "75102384-7875-4bdb-a4d5-00b17dfc6928",
      "parentId": null,
      "name": "Placide-Poulin",
      "fraction": null,
      "alias": "PLACIDE-POULIN",
      "timezone": "America/Toronto",
      "sports": [
        "Hockey"
      ],
      "type": "Ice",
      "size": "M",
      "path": "10532",
      "externalId": "7e1c2c33-8b5c-438a-936d-225f583bdbc7",
      "id": 10532,
      "venue": {
        "id": "75102384-7875-4bdb-a4d5-00b17dfc6928",
        "name": "Centre Caztel",
        "address": "905 Rte Saint-Martin",
        "city": "Sainte-Marie",
        "region": "QC",
        "postalCode": "G6E 1E6",
        "country": "Canada",
        "alias": null,
        "timezone": "America/Toronto",
        "externalId": "4ec864dc-0ef3-48b8-8c3e-5f9b1fbe2f8f"
      }
    },
    "schedule": {
      "name": "M13 AAA ÉLITE - SAISON RÉGULIÈRE",
      "type": "League",
      "division": "U13",
      "gender": "Integrated",
      "categoryId": "ba267b3e-9734-478c-a9e2-4890895cfc47",
      "startDate": "2025-09-01T00:00:00.000Z",
      "endDate": "2026-04-30T00:00:00.000Z",
      "gameFormat": "5x5",
      "seasonId": "2025-26",
      "officeId": 9175,
      "isPublic": true,
      "comments": null,
      "externalId": null,
      "id": 182366,
      "category": "AAA"
    },
    "awayTeam": {
      "HCRId": "20251183800026639",
      "name": "ALBATROS",
      "shortName": "ALBATROS",
      "division": "U13",
      "gender": "Integrated",
      "categoryId": "ba267b3e-9734-478c-a9e2-4890895cfc47",
      "seasonId": "2025-26",
      "logoId": null,
      "externalId": "1f05e5ce-433e-62f8-a08b-0627b38ad1df",
      "isPublic": true,
      "isSanctioned": true,
      "homeColor": null,
      "awayColor": null,
      "id": 128312,
      "createdAt": "2025-07-11T13:42:30.000Z",
      "updatedAt": "2026-01-15T22:58:02.449Z",
      "officeId": 5832,
      "logoUrl": "https://d1yykh3c16sa22.cloudfront.net/teams/1f05e5ce-433e-62f8-a08b-0627b38ad1df/logos/1f05e5ce-431f-6e66-9568-0627b38ad1df.jpg",
      "category": {
        "id": "ba267b3e-9734-478c-a9e2-4890895cfc47",
        "name": "U13 AAA Elite",
        "divisionId": "5904e905-ab85-4a34-85ac-9fcae9204250",
        "gender": "Integrated",
        "classId": "0b050ba5-ddd1-4759-9ad9-5ac1bf365ac7",
        "order": 1602,
        "i18n": {
          "fr": {
            "name": "M13 AAA Elite"
          }
        },
        "nameFr": "M13 AAA Elite",
        "externalId": "1f030d9f-9961-6798-8152-0666a1a64601",
        "division": {
          "id": "5904e905-ab85-4a34-85ac-9fcae9204250",
          "name": "U13",
          "shortName": "U13",
          "order": 10,
          "i18n": {
            "fr": {
              "name": "M13",
              "shortName": "M13"
            }
          }
        },
        "class": {
          "id": "0b050ba5-ddd1-4759-9ad9-5ac1bf365ac7",
          "name": "AAA",
          "shortName": "AAA",
          "order": 1,
          "i18n": {
            "fr": {
              "name": "AAA",
              "shortName": "AAA"
            }
          }
        }
      }
    },
    "homeTeam": {
      "HCRId": "20251642900026626",
      "name": "CANAM BEAUCE-APPALACHES",
      "shortName": "CANAM BEAUCE-APPALACHES",
      "division": "U13",
      "gender": "Integrated",
      "categoryId": "ba267b3e-9734-478c-a9e2-4890895cfc47",
      "seasonId": "2025-26",
      "logoId": null,
      "externalId": "1f05e5ce-41b4-690a-be7d-0627b38ad1df",
      "isPublic": true,
      "isSanctioned": true,
      "homeColor": "BLANC",
      "awayColor": "NOIR",
      "id": 128304,
      "createdAt": "2025-07-11T13:42:30.000Z",
      "updatedAt": "2025-10-23T17:50:41.271Z",
      "officeId": 6133,
      "logoUrl": "https://cdn.hcr.spordle.com/teams/1f05e5ce-41b4-690a-be7d-0627b38ad1df/logos/1f05e5ce-4194-6e3e-872e-0627b38ad1df.png",
      "category": {
        "id": "ba267b3e-9734-478c-a9e2-4890895cfc47",
        "name": "U13 AAA Elite",
        "divisionId": "5904e905-ab85-4a34-85ac-9fcae9204250",
        "gender": "Integrated",
        "classId": "0b050ba5-ddd1-4759-9ad9-5ac1bf365ac7",
        "order": 1602,
        "i18n": {
          "fr": {
            "name": "M13 AAA Elite"
          }
        },
        "nameFr": "M13 AAA Elite",
        "externalId": "1f030d9f-9961-6798-8152-0666a1a64601",
        "division": {
          "id": "5904e905-ab85-4a34-85ac-9fcae9204250",
          "name": "U13",
          "shortName": "U13",
          "order": 10,
          "i18n": {
            "fr": {
              "name": "M13",
              "shortName": "M13"
            }
          }
        },
        "class": {
          "id": "0b050ba5-ddd1-4759-9ad9-5ac1bf365ac7",
          "name": "AAA",
          "shortName": "AAA",
          "order": 1,
          "i18n": {
            "fr": {
              "name": "AAA",
              "shortName": "AAA"
            }
          }
        }
      }
    },
    "externalProviders": [],
    "isLive": false,
    "score": {
      "128304": 1,
      "128312": 4
    }
  },
  "home_team_roster": [
    {
      "teamId": 128304,
      "participantId": 795350,
      "positions": [
        "F"
      ],
      "number": 35,
      "isCaptain": false,
      "isAlternate": false,
      "isAffiliate": false,
      "isOverage": false,
      "isUnderage": false,
      "isReleased": false,
      "seasonId": "2025-26",
      "officeId": 6133,
      "externalId": "1f0880eb-65a1-64a2-b57b-02b729a8ae7b",
      "id": 2116842,
      "participant": {
        "firstName": "LOHAN",
        "lastName": "BRUNEAU",
        "alternateName": null,
        "pictureUrl": "https://cdn.hcr.spordle.com/members/1ebb653d-bf4f-642a-8f4b-068fc9a36a40/profile/small/1f0b99d5-bbe6-6b9a-bc3c-067f8c035ee7.jpg",
        "externalId": "1ebb653d-bf4f-642a-8f4b-068fc9a36a40",
        "id": 795350,
        "fullName": "LOHAN BRUNEAU"
      }
    },
    {
      "teamId": 128304,
      "participantId": 957501,
      "positions": [
        "F"
      ],
      "number": 26,
      "isCaptain": false,
      "isAlternate": false,
      "isAffiliate": false,
      "isOverage": false,
      "isUnderage": false,
      "isReleased": false,
      "seasonId": "2025-26",
      "officeId": 6133,
      "externalId": "1f0880eb-71fb-6c02-8344-02b729a8ae7b",
      "id": 2116843,
      "participant": {
        "firstName": "LOUIS",
        "lastName": "DROUIN",
        "alternateName": null,
        "pictureUrl": "https://cdn.hcr.spordle.com/members/1ebb653a-3e91-6fde-b57d-0695742fcc0e/profile/small/1f0b99dd-c39f-6be0-bafb-02ec0d6aa587.jpg",
        "externalId": "1ebb653a-3e91-6fde-b57d-0695742fcc0e",
        "id": 957501,
        "fullName": "LOUIS DROUIN"
      }
    },
    {
      "teamId": 128304,
      "participantId": 790015,
      "positions": [
        "G"
      ],
      "number": 29,
      "isCaptain": false,
      "isAlternate": false,
      "isAffiliate": false,
      "isOverage": false,
      "isUnderage": false,
      "isReleased": false,
      "seasonId": "2025-26",
      "officeId": 6133,
      "externalId": "1f0880eb-75a8-62c4-850d-02b729a8ae7b",
      "id": 2116844,
      "participant": {
        "firstName": "JEAN-PHILIPPE",
        "lastName": "GILBERT",
        "alternateName": null,
        "pictureUrl": "https://cdn.hcr.spordle.com/members/1ebb653c-739b-6ab6-9c9f-021e976b8d94/profile/small/1f0b99df-dc0a-6098-8cc0-02d85374e4dd.jpg",
        "externalId": "1ebb653c-739b-6ab6-9c9f-021e976b8d94",
        "id": 790015,
        "fullName": "JEAN-PHILIPPE GILBERT"
      }
    },
    {
      "teamId": 128304,
      "participantId": 957502,
      "positions": [
        "D"
      ],
      "number": 34,
      "isCaptain": false,
      "isAlternate": false,
      "isAffiliate": false,
      "isOverage": false,
      "isUnderage": false,
      "isReleased": false,
      "seasonId": "2025-26",
      "officeId": 6133,
      "externalId": "1f0880eb-7784-600c-9199-02b729a8ae7b",
      "id": 2116845,
      "participant": {
        "firstName": "CHARLES",
        "lastName": "LABBÉ",
        "alternateName": null,
        "pictureUrl": "https://cdn.hcr.spordle.com/members/1ebb653a-4a69-6e9c-a33e-0220ca96f6a8/profile/small/1f0b99e0-f206-6a94-ba52-02d85374e4dd.jpg",
        "externalId": "1ebb653a-4a69-6e9c-a33e-0220ca96f6a8",
        "id": 957502,
        "fullName": "CHARLES LABBÉ"
      }
    },
    {
      "teamId": 128304,
      "participantId": 957504,
      "positions": [
        "F"
      ],
      "number": 27,
      "isCaptain": false,
      "isAlternate": false,
      "isAffiliate": false,
      "isOverage": false,
      "isUnderage": false,
      "isReleased": false,
      "seasonId": "2025-26",
      "officeId": 6133,
      "externalId": "1f0880eb-73ea-6be4-bc2b-02b729a8ae7b",
      "id": 2116846,
      "participant": {
        "firstName": "GABRIEL",
        "lastName": "GARNEAU",
        "alternateName": null,
        "pictureUrl": "https://cdn.hcr.spordle.com/members/1ebb653e-1e77-634e-84d2-021e976b8d94/profile/small/1f0b99de-c074-6686-a12c-02d85374e4dd.jpg",
        "externalId": "1ebb653e-1e77-634e-84d2-021e976b8d94",
        "id": 957504,
        "fullName": "GABRIEL GARNEAU"
      }
    },
    {
      "teamId": 128304,
      "participantId": 957503,
      "positions": [
        "F"
      ],
      "number": 38,
      "isCaptain": false,
      "isAlternate": false,
      "isAffiliate": false,
      "isOverage": false,
      "isUnderage": false,
      "isReleased": false,
      "seasonId": "2025-26",
      "officeId": 6133,
      "externalId": "1f0880eb-6176-60e4-9fc8-02b729a8ae7b",
      "id": 2116847,
      "participant": {
        "firstName": "ELIJAH",
        "lastName": "BELANGER",
        "alternateName": null,
        "pictureUrl": "https://cdn.hcr.spordle.com/members/1ebb653d-ae71-6752-80bb-020a2d3ab872/profile/small/1f0b99d3-85c1-6e7c-a2f8-067f8c035ee7.jpg",
        "externalId": "1ebb653d-ae71-6752-80bb-020a2d3ab872",
        "id": 957503,
        "fullName": "ELIJAH BELANGER"
      }
    },
    {
      "teamId": 128304,
      "participantId": 818183,
      "positions": [
        "D"
      ],
      "number": 5,
      "isCaptain": false,
      "isAlternate": false,
      "isAffiliate": false,
      "isOverage": false,
      "isUnderage": false,
      "isReleased": false,
      "seasonId": "2025-26",
      "officeId": 6133,
      "externalId": "1f0880eb-797d-6cbe-ace4-02b729a8ae7b",
      "id": 2116848,
      "participant": {
        "firstName": "ALEX",
        "lastName": "LEMAY",
        "alternateName": null,
        "pictureUrl": "https://cdn.hcr.spordle.com/members/1ebb6536-89e6-6696-be94-020a2d3ab872/profile/small/1f0b99e1-e8b5-6b9c-b39f-067f8c035ee7.jpg",
        "externalId": "1ebb6536-89e6-6696-be94-020a2d3ab872",
        "id": 818183,
        "fullName": "ALEX LEMAY"
      }
    },
    {
      "teamId": 128304,
      "participantId": 957505,
      "positions": [
        "F"
      ],
      "number": 28,
      "isCaptain": false,
      "isAlternate": false,
      "isAffiliate": false,
      "isOverage": false,
      "isUnderage": false,
      "isReleased": false,
      "seasonId": "2025-26",
      "officeId": 6133,
      "externalId": "1f0880eb-6b8c-64ca-a0dc-02b729a8ae7b",
      "id": 2116849,
      "participant": {
        "firstName": "HUBERT",
        "lastName": "CORRIVEAU",
        "alternateName": null,
        "pictureUrl": "https://cdn.hcr.spordle.com/members/1ebb653f-b65c-6500-9488-020a2d3ab872/profile/small/1f0b99dc-a7ea-63f6-847d-067f8c035ee7.jpg",
        "externalId": "1ebb653f-b65c-6500-9488-020a2d3ab872",
        "id": 957505,
        "fullName": "HUBERT CORRIVEAU"
      }
    },
    {
      "teamId": 128304,
      "participantId": 957506,
      "positions": [
        "D"
      ],
      "number": 43,
      "isCaptain": false,
      "isAlternate": false,
      "isAffiliate": false,
      "isOverage": false,
      "isUnderage": false,
      "isReleased": false,
      "seasonId": "2025-26",
      "officeId": 6133,
      "externalId": "1f0880eb-5fca-6f38-b5cd-02b729a8ae7b",
      "id": 2116850,
      "participant": {
        "firstName": "HUBERT",
        "lastName": "BAILLARGEON",
        "alternateName": null,
        "pictureUrl": "https://cdn.hcr.spordle.com/members/1ebb653c-4e32-607c-984f-0695742fcc0e/profile/small/1f0b99d2-59de-6536-8a6a-02d85374e4dd.jpg",
        "externalId": "1ebb653c-4e32-607c-984f-0695742fcc0e",
        "id": 957506,
        "fullName": "HUBERT BAILLARGEON"
      }
    },
    {
      "teamId": 128304,
      "participantId": 957507,
      "positions": [
        "F"
      ],
      "number": 47,
      "isCaptain": false,
      "isAlternate": false,
      "isAffiliate": false,
      "isOverage": false,
      "isUnderage": false,
      "isReleased": false,
      "seasonId": "2025-26",
      "officeId": 6133,
      "externalId": "1f0880eb-7b2b-6e12-a31b-02b729a8ae7b",
      "id": 2116851,
      "participant": {
        "firstName": "DONOVAN",
        "lastName": "LESSARD",
        "alternateName": null,
        "pictureUrl": "https://cdn.hcr.spordle.com/members/1ebb653a-085d-6a62-b4c1-06803bcf766a/profile/small/1f0b99e2-e59c-6d06-8aa4-067f8c035ee7.jpg",
        "externalId": "1ebb653a-085d-6a62-b4c1-06803bcf766a",
        "id": 957507,
        "fullName": "DONOVAN LESSARD"
      }
    },
    {
      "teamId": 128304,
      "participantId": 957508,
      "positions": [
        "D"
      ],
      "number": 36,
      "isCaptain": false,
      "isAlternate": false,
      "isAffiliate": false,
      "isOverage": false,
      "isUnderage": false,
      "isReleased": false,
      "seasonId": "2025-26",
      "officeId": 6133,
      "externalId": "1f0880eb-8992-6bb8-92ff-02b729a8ae7b",
      "id": 2116852,
      "participant": {
        "firstName": "GABRIEL",
        "lastName": "VERPAELST",
        "alternateName": null,
        "pictureUrl": "https://cdn.hcr.spordle.com/members/1ebb653a-3053-6800-be43-06803bcf766a/profile/small/1f0b99d7-4eef-6f08-b134-02ec0d6aa587.jpg",
        "externalId": "1ebb653a-3053-6800-be43-06803bcf766a",
        "id": 957508,
        "fullName": "GABRIEL VERPAELST"
      }
    },
    {
      "teamId": 128304,
      "participantId": 957509,
      "positions": [
        "D"
      ],
      "number": 41,
      "isCaptain": false,
      "isAlternate": false,
      "isAffiliate": false,
      "isOverage": false,
      "isUnderage": false,
      "isReleased": false,
      "seasonId": "2025-26",
      "officeId": 6133,
      "externalId": "1f0880eb-87af-69e0-ab2e-02b729a8ae7b",
      "id": 2116853,
      "participant": {
        "firstName": "MILAN",
        "lastName": "VACHON",
        "alternateName": null,
        "pictureUrl": "https://cdn.hcr.spordle.com/members/1ebb653e-151d-6406-88a8-021e976b8d94/profile/small/1f0b99ea-3c24-6f46-bb35-02ec0d6aa587.jpg",
        "externalId": "1ebb653e-151d-6406-88a8-021e976b8d94",
        "id": 957509,
        "fullName": "MILAN VACHON"
      }
    },
    {
      "teamId": 128304,
      "participantId": 771531,
      "positions": [
        "G"
      ],
      "number": 39,
      "isCaptain": false,
      "isAlternate": false,
      "isAffiliate": false,
      "isOverage": false,
      "isUnderage": false,
      "isReleased": false,
      "seasonId": "2025-26",
      "officeId": 6133,
      "externalId": "1f0880eb-81ee-6b96-a879-02b729a8ae7b",
      "id": 2116854,
      "participant": {
        "firstName": "KALEB",
        "lastName": "PATRY",
        "alternateName": null,
        "pictureUrl": "https://cdn.hcr.spordle.com/members/1ebb653e-1be7-6e58-8294-020a2d3ab872/profile/small/1f0b99e7-1044-64ec-9d27-02ec0d6aa587.jpg",
        "externalId": "1ebb653e-1be7-6e58-8294-020a2d3ab872",
        "id": 771531,
        "fullName": "KALEB PATRY"
      }
    },
    {
      "teamId": 128304,
      "participantId": 957510,
      "positions": [
        "F"
      ],
      "number": 40,
      "isCaptain": false,
      "isAlternate": false,
      "isAffiliate": false,
      "isOverage": false,
      "isUnderage": false,
      "isReleased": false,
      "seasonId": "2025-26",
      "officeId": 6133,
      "externalId": "1f0880eb-85ed-624c-98d2-02b729a8ae7b",
      "id": 2116855,
      "participant": {
        "firstName": "JUSTIN",
        "lastName": "TANGUAY",
        "alternateName": null,
        "pictureUrl": "https://cdn.hcr.spordle.com/members/1ebb653f-4c41-653a-9a95-021e976b8d94/profile/small/1f0b99e9-1fe9-6a94-bc84-02ec0d6aa587.jpg",
        "externalId": "1ebb653f-4c41-653a-9a95-021e976b8d94",
        "id": 957510,
        "fullName": "JUSTIN TANGUAY"
      }
    },
    {
      "teamId": 128304,
      "participantId": 957511,
      "positions": [
        "D"
      ],
      "number": 2,
      "isCaptain": false,
      "isAlternate": false,
      "isAffiliate": false,
      "isOverage": false,
      "isUnderage": false,
      "isReleased": false,
      "seasonId": "2025-26",
      "officeId": 6133,
      "externalId": "1f0880eb-83a5-6354-ab19-02b729a8ae7b",
      "id": 2116856,
      "participant": {
        "firstName": "NATAN",
        "lastName": "ROY",
        "alternateName": null,
        "pictureUrl": "https://cdn.hcr.spordle.com/members/1ebb653c-0d4b-6306-a5be-068fc9a36a40/profile/small/1f0b99e8-319b-6eb4-8841-02ec0d6aa587.jpg",
        "externalId": "1ebb653c-0d4b-6306-a5be-068fc9a36a40",
        "id": 957511,
        "fullName": "NATAN ROY"
      }
    },
    {
      "teamId": 128304,
      "participantId": 957514,
      "positions": [
        "F"
      ],
      "number": 25,
      "isCaptain": false,
      "isAlternate": false,
      "isAffiliate": false,
      "isOverage": false,
      "isUnderage": false,
      "isReleased": false,
      "seasonId": "2025-26",
      "officeId": 6133,
      "externalId": "1f0880eb-8043-6198-b838-02b729a8ae7b",
      "id": 2116857,
      "participant": {
        "firstName": "JAMES",
        "lastName": "MOORE",
        "alternateName": null,
        "pictureUrl": "https://cdn.hcr.spordle.com/members/1ebb653a-5660-6200-9d03-0220ca96f6a8/profile/small/1f0b99e6-05f5-651e-a66f-02ec0d6aa587.jpg",
        "externalId": "1ebb653a-5660-6200-9d03-0220ca96f6a8",
        "id": 957514,
        "fullName": "JAMES MOORE"
      }
    },
    {
      "teamId": 128304,
      "participantId": 957513,
      "positions": [
        "F"
      ],
      "number": 42,
      "isCaptain": false,
      "isAlternate": false,
      "isAffiliate": false,
      "isOverage": false,
      "isUnderage": false,
      "isReleased": false,
      "seasonId": "2025-26",
      "officeId": 6133,
      "externalId": "1f0880eb-7ce1-6892-9eb0-02b729a8ae7b",
      "id": 2116858,
      "participant": {
        "firstName": "MATHIEU",
        "lastName": "LESSARD",
        "alternateName": null,
        "pictureUrl": "https://cdn.hcr.spordle.com/members/1ebb653c-09fe-6db0-9505-0695742fcc0e/profile/small/1f0b99e4-07c4-6414-8e8b-067f8c035ee7.jpg",
        "externalId": "1ebb653c-09fe-6db0-9505-0695742fcc0e",
        "id": 957513,
        "fullName": "MATHIEU LESSARD"
      }
    },
    {
      "teamId": 128304,
      "participantId": 957512,
      "positions": [
        "F"
      ],
      "number": 37,
      "isCaptain": false,
      "isAlternate": false,
      "isAffiliate": false,
      "isOverage": false,
      "isUnderage": false,
      "isReleased": false,
      "seasonId": "2025-26",
      "officeId": 6133,
      "externalId": "1f0880eb-7e8e-6f0a-bb63-02b729a8ae7b",
      "id": 2116859,
      "participant": {
        "firstName": "LAURENT",
        "lastName": "MATHIEU",
        "alternateName": null,
        "pictureUrl": "https://cdn.hcr.spordle.com/members/1ebb653a-4b9c-6378-8a8a-020a2d3ab872/profile/small/1f0b99e5-1047-6ea0-8925-067f8c035ee7.jpg",
        "externalId": "1ebb653a-4b9c-6378-8a8a-020a2d3ab872",
        "id": 957512,
        "fullName": "LAURENT MATHIEU"
      }
    },
    {
      "teamId": 128304,
      "participantId": 958421,
      "positions": [
        "Head Coach"
      ],
      "number": null,
      "isCaptain": false,
      "isAlternate": false,
      "isAffiliate": false,
      "isOverage": false,
      "isUnderage": false,
      "isReleased": false,
      "seasonId": "2025-26",
      "officeId": 6133,
      "externalId": "1f08cc74-6779-67be-82fa-02b729a8ae7b",
      "id": 2130792,
      "participant": {
        "firstName": "JEAN-FRANÇOIS",
        "lastName": "CIMON",
        "alternateName": null,
        "pictureUrl": null,
        "externalId": "1ebb6529-0101-6e00-88f6-068fc9a36a40",
        "id": 958421,
        "fullName": "JEAN-FRANÇOIS CIMON"
      }
    },
    {
      "teamId": 128304,
      "participantId": 797875,
      "positions": [
        "Assistant Coach"
      ],
      "number": null,
      "isCaptain": false,
      "isAlternate": false,
      "isAffiliate": false,
      "isOverage": false,
      "isUnderage": false,
      "isReleased": false,
      "seasonId": "2025-26",
      "officeId": 6133,
      "externalId": "1f08d810-bfe2-6c1e-990d-026d5f4e9419",
      "id": 2133714,
      "participant": {
        "firstName": "SIMON",
        "lastName": "LAROUCHE",
        "alternateName": null,
        "pictureUrl": null,
        "externalId": "1ebb653a-5c25-6122-9fc3-068fc9a36a40",
        "id": 797875,
        "fullName": "SIMON LAROUCHE"
      }
    },
    {
      "teamId": 128304,
      "participantId": 961090,
      "positions": [
        "D"
      ],
      "number": 0,
      "isCaptain": false,
      "isAlternate": false,
      "isAffiliate": true,
      "isOverage": false,
      "isUnderage": false,
      "isReleased": false,
      "seasonId": "2025-26",
      "officeId": 6133,
      "externalId": "1f08d8b1-8b5d-67fe-a230-026d5f4e9419",
      "id": 2133963,
      "participant": {
        "firstName": "LOIC",
        "lastName": "GROLEAU",
        "alternateName": null,
        "pictureUrl": "https://cdn.hcr.spordle.com/members/1ebb653a-186f-6522-b178-06803bcf766a/profile/small/1f0b9af5-0ba5-6558-b27c-02d85374e4dd.jpg",
        "externalId": "1ebb653a-186f-6522-b178-06803bcf766a",
        "id": 961090,
        "fullName": "LOIC GROLEAU"
      }
    },
    {
      "teamId": 128304,
      "participantId": 961102,
      "positions": [
        "F"
      ],
      "number": 0,
      "isCaptain": false,
      "isAlternate": false,
      "isAffiliate": true,
      "isOverage": false,
      "isUnderage": false,
      "isReleased": false,
      "seasonId": "2025-26",
      "officeId": 6133,
      "externalId": "1f08d8b1-8823-6548-8700-026d5f4e9419",
      "id": 2133964,
      "participant": {
        "firstName": "LOIC",
        "lastName": "NADEAU",
        "alternateName": null,
        "pictureUrl": "https://cdn.hcr.spordle.com/members/1ebb653a-494d-6e32-8986-0220ca96f6a8/profile/small/1f0b9af8-cba9-6f68-a14a-02ec0d6aa587.jpg",
        "externalId": "1ebb653a-494d-6e32-8986-0220ca96f6a8",
        "id": 961102,
        "fullName": "LOIC NADEAU"
      }
    },
    {
      "teamId": 128304,
      "participantId": 795201,
      "positions": [
        "F"
      ],
      "number": 0,
      "isCaptain": false,
      "isAlternate": false,
      "isAffiliate": true,
      "isOverage": false,
      "isUnderage": false,
      "isReleased": false,
      "seasonId": "2025-26",
      "officeId": 6133,
      "externalId": "1f08d8b1-868d-6cb0-9131-026d5f4e9419",
      "id": 2133965,
      "participant": {
        "firstName": "MAYSON",
        "lastName": "FECTEAU",
        "alternateName": null,
        "pictureUrl": "https://cdn.hcr.spordle.com/members/1ebb653c-7be2-622e-a921-06803bcf766a/profile/small/1f0b9af2-da95-6f0a-8853-02ec0d6aa587.jpg",
        "externalId": "1ebb653c-7be2-622e-a921-06803bcf766a",
        "id": 795201,
        "fullName": "MAYSON FECTEAU"
      }
    },
    {
      "teamId": 128304,
      "participantId": 957484,
      "positions": [
        "G"
      ],
      "number": 0,
      "isCaptain": false,
      "isAlternate": false,
      "isAffiliate": true,
      "isOverage": false,
      "isUnderage": false,
      "isReleased": false,
      "seasonId": "2025-26",
      "officeId": 6133,
      "externalId": "1f08d8b1-8eb7-6a62-8d09-026d5f4e9419",
      "id": 2133966,
      "participant": {
        "firstName": "LOUIS-PIERRE",
        "lastName": "POULIN",
        "alternateName": null,
        "pictureUrl": "https://cdn.hcr.spordle.com/members/1ebb653c-873a-68ba-9b26-0695742fcc0e/profile/small/1f0b9b1c-2b83-65f6-8b63-02d85374e4dd.jpg",
        "externalId": "1ebb653c-873a-68ba-9b26-0695742fcc0e",
        "id": 957484,
        "fullName": "LOUIS-PIERRE POULIN"
      }
    },
    {
      "teamId": 128304,
      "participantId": 957483,
      "positions": [
        "G"
      ],
      "number": 0,
      "isCaptain": false,
      "isAlternate": false,
      "isAffiliate": true,
      "isOverage": false,
      "isUnderage": false,
      "isReleased": false,
      "seasonId": "2025-26",
      "officeId": 6133,
      "externalId": "1f08d8b1-8d19-60ca-a712-026d5f4e9419",
      "id": 2133967,
      "participant": {
        "firstName": "ANTHONY",
        "lastName": "CARRIER",
        "alternateName": null,
        "pictureUrl": "https://cdn.hcr.spordle.com/members/1ebb653e-1bd6-65ea-a2b7-0695742fcc0e/profile/small/1f0b9aee-d2a5-6a2e-9eb6-02ec0d6aa587.jpg",
        "externalId": "1ebb653e-1bd6-65ea-a2b7-0695742fcc0e",
        "id": 957483,
        "fullName": "ANTHONY CARRIER"
      }
    },
    {
      "teamId": 128304,
      "participantId": 790010,
      "positions": [
        "D"
      ],
      "number": 0,
      "isCaptain": false,
      "isAlternate": false,
      "isAffiliate": true,
      "isOverage": false,
      "isUnderage": false,
      "isReleased": false,
      "seasonId": "2025-26",
      "officeId": 6133,
      "externalId": "1f08d8b1-89c6-6cc4-bc23-026d5f4e9419",
      "id": 2133968,
      "participant": {
        "firstName": "ANTOINE",
        "lastName": "LAROCHE",
        "alternateName": null,
        "pictureUrl": "https://cdn.hcr.spordle.com/members/1ebb6529-95d7-6142-92b4-068fc9a36a40/profile/small/1f0b9af6-64ae-6220-8b52-02ec0d6aa587.jpg",
        "externalId": "1ebb6529-95d7-6142-92b4-068fc9a36a40",
        "id": 790010,
        "fullName": "ANTOINE LAROCHE"
      }
    },
    {
      "teamId": 128304,
      "participantId": 961088,
      "positions": [
        "F"
      ],
      "number": 0,
      "isCaptain": false,
      "isAlternate": false,
      "isAffiliate": true,
      "isOverage": false,
      "isUnderage": false,
      "isReleased": false,
      "seasonId": "2025-26",
      "officeId": 6133,
      "externalId": "1f08d8b1-84fa-6510-8a22-026d5f4e9419",
      "id": 2133969,
      "participant": {
        "firstName": "JAEL",
        "lastName": "GOUPIL",
        "alternateName": null,
        "pictureUrl": "https://cdn.hcr.spordle.com/members/1ebb6527-5356-686a-a925-0220ca96f6a8/profile/small/1f0b9af4-5f29-6acc-a28a-02ec0d6aa587.jpg",
        "externalId": "1ebb6527-5356-686a-a925-0220ca96f6a8",
        "id": 961088,
        "fullName": "JAEL GOUPIL"
      }
    },
    {
      "teamId": 128304,
      "participantId": 968461,
      "positions": [
        "Assistant Coach"
      ],
      "number": null,
      "isCaptain": false,
      "isAlternate": false,
      "isAffiliate": false,
      "isOverage": false,
      "isUnderage": false,
      "isReleased": false,
      "seasonId": "2025-26",
      "officeId": 6133,
      "externalId": "1f094926-74f9-6d60-b6b7-0266c5750d21",
      "id": 2164847,
      "participant": {
        "firstName": "VINCENT",
        "lastName": "DOYON",
        "alternateName": null,
        "pictureUrl": null,
        "externalId": "1ebb653d-fa14-69d4-a00b-021e976b8d94",
        "id": 968461,
        "fullName": "VINCENT DOYON"
      }
    },
    {
      "teamId": 128304,
      "participantId": 930456,
      "positions": [
        "F"
      ],
      "number": 0,
      "isCaptain": false,
      "isAlternate": false,
      "isAffiliate": true,
      "isOverage": false,
      "isUnderage": false,
      "isReleased": false,
      "seasonId": "2025-26",
      "officeId": 6133,
      "externalId": "1f09ae02-8be7-6284-9cc1-02d448fac679",
      "id": 2218496,
      "participant": {
        "firstName": "ALEXANDRE",
        "lastName": "LAPLANTE",
        "alternateName": null,
        "pictureUrl": null,
        "externalId": "1ebb653a-5fc1-6060-a631-0695742fcc0e",
        "id": 930456,
        "fullName": "ALEXANDRE LAPLANTE"
      }
    },
    {
      "teamId": 128304,
      "participantId": 795332,
      "positions": [
        "D"
      ],
      "number": 0,
      "isCaptain": false,
      "isAlternate": false,
      "isAffiliate": true,
      "isOverage": false,
      "isUnderage": false,
      "isReleased": false,
      "seasonId": "2025-26",
      "officeId": 6133,
      "externalId": "1f09ae05-1f12-6dd6-ae8a-0697e30e3c49",
      "id": 2218524,
      "participant": {
        "firstName": "LUDOVICK",
        "lastName": "JACQUES",
        "alternateName": null,
        "pictureUrl": null,
        "externalId": "1ebb6527-8acd-6bcc-8c98-068fc9a36a40",
        "id": 795332,
        "fullName": "LUDOVICK JACQUES"
      }
    },
    {
      "teamId": 128304,
      "participantId": 964437,
      "positions": [
        "G"
      ],
      "number": 0,
      "isCaptain": false,
      "isAlternate": false,
      "isAffiliate": true,
      "isOverage": false,
      "isUnderage": false,
      "isReleased": false,
      "seasonId": "2025-26",
      "officeId": 6133,
      "externalId": "1f09ae07-4067-6606-bf13-02d448fac679",
      "id": 2218534,
      "participant": {
        "firstName": "FÉLIX-ANTOINE",
        "lastName": "POULIN",
        "alternateName": null,
        "pictureUrl": null,
        "externalId": "1ebb6529-584d-6952-b3bb-068fc9a36a40",
        "id": 964437,
        "fullName": "FÉLIX-ANTOINE POULIN"
      }
    },
    {
      "teamId": 128304,
      "participantId": 996391,
      "positions": [
        "D"
      ],
      "number": 0,
      "isCaptain": false,
      "isAlternate": false,
      "isAffiliate": true,
      "isOverage": false,
      "isUnderage": false,
      "isReleased": false,
      "seasonId": "2025-26",
      "officeId": 6133,
      "externalId": "1f0a2e9c-0219-6032-b331-061c8b8d0863",
      "id": 2321556,
      "participant": {
        "firstName": "WILLIAM",
        "lastName": "LANGEVIN",
        "alternateName": null,
        "pictureUrl": null,
        "externalId": "1ebb653a-4602-6c1e-87f7-0220ca96f6a8",
        "id": 996391,
        "fullName": "WILLIAM LANGEVIN"
      }
    },
    {
      "teamId": 128304,
      "participantId": 795334,
      "positions": [
        "F"
      ],
      "number": 0,
      "isCaptain": false,
      "isAlternate": false,
      "isAffiliate": true,
      "isOverage": false,
      "isUnderage": false,
      "isReleased": false,
      "seasonId": "2025-26",
      "officeId": 6133,
      "externalId": "1f0aa925-1374-65e4-83be-067f8c035ee7",
      "id": 2408469,
      "participant": {
        "firstName": "NOAH",
        "lastName": "JOLICOEUR",
        "alternateName": null,
        "pictureUrl": "https://cdn.hcr.spordle.com/members/1ebb6527-404b-6afe-a63b-0695742fcc0e/profile/small/1f0c5a96-ab48-6cfc-bbca-022a1523c89f.jpg",
        "externalId": "1ebb6527-404b-6afe-a63b-0695742fcc0e",
        "id": 795334,
        "fullName": "NOAH JOLICOEUR"
      }
    },
    {
      "teamId": 128304,
      "participantId": 795336,
      "positions": [
        "F"
      ],
      "number": 0,
      "isCaptain": false,
      "isAlternate": false,
      "isAffiliate": true,
      "isOverage": false,
      "isUnderage": false,
      "isReleased": false,
      "seasonId": "2025-26",
      "officeId": 6133,
      "externalId": "1f0aa935-60ba-6b90-b06f-02d85374e4dd",
      "id": 2408553,
      "participant": {
        "firstName": "ZACKARY",
        "lastName": "CLOUTIER",
        "alternateName": null,
        "pictureUrl": "https://cdn.hcr.spordle.com/members/1ebb653e-1c5b-6f74-a10a-0695742fcc0e/profile/small/1f0b9af0-296b-6f42-a970-067f8c035ee7.jpg",
        "externalId": "1ebb653e-1c5b-6f74-a10a-0695742fcc0e",
        "id": 795336,
        "fullName": "ZACKARY CLOUTIER"
      }
    },
    {
      "teamId": 128304,
      "participantId": 961103,
      "positions": [
        "F"
      ],
      "number": 0,
      "isCaptain": false,
      "isAlternate": false,
      "isAffiliate": true,
      "isOverage": false,
      "isUnderage": false,
      "isReleased": false,
      "seasonId": "2025-26",
      "officeId": 6133,
      "externalId": "1f0aa935-6351-63fe-98a9-02d85374e4dd",
      "id": 2408554,
      "participant": {
        "firstName": "NATHAN",
        "lastName": "TANGUAY",
        "alternateName": null,
        "pictureUrl": "https://cdn.hcr.spordle.com/members/1ebb653f-4f14-676c-b7ed-021e976b8d94/profile/small/1f0b9b1c-e9c0-6000-8a75-02d85374e4dd.jpg",
        "externalId": "1ebb653f-4f14-676c-b7ed-021e976b8d94",
        "id": 961103,
        "fullName": "NATHAN TANGUAY"
      }
    },
    {
      "teamId": 128304,
      "participantId": 961101,
      "positions": [
        "F"
      ],
      "number": 0,
      "isCaptain": false,
      "isAlternate": false,
      "isAffiliate": true,
      "isOverage": false,
      "isUnderage": false,
      "isReleased": false,
      "seasonId": "2025-26",
      "officeId": 6133,
      "externalId": "1f0aa935-6206-6576-8e59-02d85374e4dd",
      "id": 2408555,
      "participant": {
        "firstName": "SAMUEL",
        "lastName": "MAHEUX",
        "alternateName": null,
        "pictureUrl": "https://cdn.hcr.spordle.com/members/1ed0ff2f-38f7-641c-9a9e-02f1899482f4/profile/small/1f0b9af7-f597-62b8-86bd-02ec0d6aa587.jpg",
        "externalId": "1ed0ff2f-38f7-641c-9a9e-02f1899482f4",
        "id": 961101,
        "fullName": "SAMUEL MAHEUX"
      }
    },
    {
      "teamId": 128304,
      "participantId": 961087,
      "positions": [
        "F"
      ],
      "number": 0,
      "isCaptain": false,
      "isAlternate": false,
      "isAffiliate": true,
      "isOverage": false,
      "isUnderage": false,
      "isReleased": false,
      "seasonId": "2025-26",
      "officeId": 6133,
      "externalId": "1f0aa937-e8d3-64bc-a615-02d85374e4dd",
      "id": 2408564,
      "participant": {
        "firstName": "ÉLIOT",
        "lastName": "GILBERT",
        "alternateName": null,
        "pictureUrl": "https://cdn.hcr.spordle.com/members/1ebb653c-5a93-6e7e-be4c-0220ca96f6a8/profile/small/1f0b9af3-ad16-6bd2-b960-067f8c035ee7.jpg",
        "externalId": "1ebb653c-5a93-6e7e-be4c-0220ca96f6a8",
        "id": 961087,
        "fullName": "ÉLIOT GILBERT"
      }
    }
  ],
  "away_team_roster": [
    {
      "teamId": 128312,
      "participantId": 955001,
      "positions": [
        "F"
      ],
      "number": 34,
      "isCaptain": false,
      "isAlternate": false,
      "isAffiliate": false,
      "isOverage": false,
      "isUnderage": false,
      "isReleased": false,
      "seasonId": "2025-26",
      "officeId": 5832,
      "externalId": "1f08270e-e8b7-6350-874a-06d853421783",
      "id": 2104639,
      "participant": {
        "firstName": "LOUIS",
        "lastName": "TREMBLAY",
        "alternateName": null,
        "pictureUrl": "https://cdn.hcr.spordle.com/members/1ebb64e0-4192-6cce-a2d0-021e976b8d94/profile/small/1f0be443-d389-6a32-8fa6-02ec0d6aa587.jpg",
        "externalId": "1ebb64e0-4192-6cce-a2d0-021e976b8d94",
        "id": 955001,
        "fullName": "LOUIS TREMBLAY"
      }
    },
    {
      "teamId": 128312,
      "participantId": 955003,
      "positions": [
        "F"
      ],
      "number": 47,
      "isCaptain": false,
      "isAlternate": false,
      "isAffiliate": false,
      "isOverage": false,
      "isUnderage": false,
      "isReleased": false,
      "seasonId": "2025-26",
      "officeId": 5832,
      "externalId": "1f08270e-e3e9-6256-9fd5-06d853421783",
      "id": 2104640,
      "participant": {
        "firstName": "HUBERT",
        "lastName": "MORNEAU",
        "alternateName": null,
        "pictureUrl": "https://cdn.hcr.spordle.com/members/1ebb64e1-c4c1-6ebe-9b63-020a2d3ab872/profile/small/1f0be441-5c32-6f9e-a85e-067f8c035ee7.jpg",
        "externalId": "1ebb64e1-c4c1-6ebe-9b63-020a2d3ab872",
        "id": 955003,
        "fullName": "HUBERT MORNEAU"
      }
    },
    {
      "teamId": 128312,
      "participantId": 955002,
      "positions": [
        "C"
      ],
      "number": 89,
      "isCaptain": false,
      "isAlternate": false,
      "isAffiliate": false,
      "isOverage": false,
      "isUnderage": false,
      "isReleased": false,
      "seasonId": "2025-26",
      "officeId": 5832,
      "externalId": "1f08270e-df37-68f2-92d7-06d853421783",
      "id": 2104641,
      "participant": {
        "firstName": "THÉO",
        "lastName": "GAUTHIER",
        "alternateName": null,
        "pictureUrl": "https://cdn.hcr.spordle.com/members/1ebb64e0-3796-67e8-b418-06803bcf766a/profile/small/1f0be43d-ab63-6c20-8d97-02ec0d6aa587.jpg",
        "externalId": "1ebb64e0-3796-67e8-b418-06803bcf766a",
        "id": 955002,
        "fullName": "THÉO GAUTHIER"
      }
    },
    {
      "teamId": 128312,
      "participantId": 955004,
      "positions": [
        "F"
      ],
      "number": 88,
      "isCaptain": false,
      "isAlternate": false,
      "isAffiliate": false,
      "isOverage": false,
      "isUnderage": false,
      "isReleased": false,
      "seasonId": "2025-26",
      "officeId": 5832,
      "externalId": "1f08270e-ea40-6528-b5e5-06d853421783",
      "id": 2104642,
      "participant": {
        "firstName": "ZAKARY",
        "lastName": "LITALIEN",
        "alternateName": null,
        "pictureUrl": null,
        "externalId": "1ebb64ed-fe92-6f56-8c07-06803bcf766a",
        "id": 955004,
        "fullName": "ZAKARY LITALIEN"
      }
    },
    {
      "teamId": 128312,
      "participantId": 814079,
      "positions": [
        "C"
      ],
      "number": 22,
      "isCaptain": false,
      "isAlternate": false,
      "isAffiliate": false,
      "isOverage": false,
      "isUnderage": false,
      "isReleased": false,
      "seasonId": "2025-26",
      "officeId": 5832,
      "externalId": "1f08270e-e5a8-6b96-ac2e-06d853421783",
      "id": 2104643,
      "participant": {
        "firstName": "LOÏC",
        "lastName": "GRENIER",
        "alternateName": null,
        "pictureUrl": null,
        "externalId": "1ebb6591-d97e-6702-a9c4-06798f358960",
        "id": 814079,
        "fullName": "LOÏC GRENIER"
      }
    },
    {
      "teamId": 128312,
      "participantId": 955006,
      "positions": [
        "F"
      ],
      "number": 27,
      "isCaptain": false,
      "isAlternate": false,
      "isAffiliate": false,
      "isOverage": false,
      "isUnderage": false,
      "isReleased": false,
      "seasonId": "2025-26",
      "officeId": 5832,
      "externalId": "1f08270e-e0c2-65a0-8b12-06d853421783",
      "id": 2104644,
      "participant": {
        "firstName": "CLEMENT",
        "lastName": "DUGAS",
        "alternateName": null,
        "pictureUrl": null,
        "externalId": "1ebb64e2-5c8b-60b0-96b9-0695742fcc0e",
        "id": 955006,
        "fullName": "CLEMENT DUGAS"
      }
    },
    {
      "teamId": 128312,
      "participantId": 955005,
      "positions": [
        "F"
      ],
      "number": 8,
      "isCaptain": false,
      "isAlternate": false,
      "isAffiliate": false,
      "isOverage": false,
      "isUnderage": false,
      "isReleased": false,
      "seasonId": "2025-26",
      "officeId": 5832,
      "externalId": "1f08270e-ddb2-6734-ab8d-06d853421783",
      "id": 2104645,
      "participant": {
        "firstName": "ZACK",
        "lastName": "CYR",
        "alternateName": null,
        "pictureUrl": "https://cdn.hcr.spordle.com/members/1ebb6591-de78-6e88-a4e2-0220ca96f6a8/profile/small/1f0be438-d959-606c-8b76-067f8c035ee7.jpg",
        "externalId": "1ebb6591-de78-6e88-a4e2-0220ca96f6a8",
        "id": 955005,
        "fullName": "ZACK CYR"
      }
    },
    {
      "teamId": 128312,
      "participantId": 955007,
      "positions": [
        "C"
      ],
      "number": 14,
      "isCaptain": false,
      "isAlternate": false,
      "isAffiliate": false,
      "isOverage": false,
      "isUnderage": false,
      "isReleased": false,
      "seasonId": "2025-26",
      "officeId": 5832,
      "externalId": "1f08270e-e244-673e-8b84-06d853421783",
      "id": 2104646,
      "participant": {
        "firstName": "MALIK",
        "lastName": "MIOUSE",
        "alternateName": null,
        "pictureUrl": null,
        "externalId": "1ebb64e0-2f83-6ea2-9464-021e976b8d94",
        "id": 955007,
        "fullName": "MALIK MIOUSE"
      }
    },
    {
      "teamId": 128312,
      "participantId": 955009,
      "positions": [
        "F"
      ],
      "number": 29,
      "isCaptain": false,
      "isAlternate": false,
      "isAffiliate": false,
      "isOverage": false,
      "isUnderage": false,
      "isReleased": false,
      "seasonId": "2025-26",
      "officeId": 5832,
      "externalId": "1f08270e-ebc5-6cd6-98db-06d853421783",
      "id": 2104647,
      "participant": {
        "firstName": "FLORA-MAY",
        "lastName": "CHOUINARD",
        "alternateName": null,
        "pictureUrl": "https://cdn.hcr.spordle.com/members/1ec41712-7ac7-6282-b8f1-0200963e0a9c/profile/small/1f0be437-2a0f-6490-9ef6-02d85374e4dd.jpg",
        "externalId": "1ec41712-7ac7-6282-b8f1-0200963e0a9c",
        "id": 955009,
        "fullName": "FLORA-MAY CHOUINARD"
      }
    },
    {
      "teamId": 128312,
      "participantId": 955008,
      "positions": [
        "C"
      ],
      "number": 98,
      "isCaptain": false,
      "isAlternate": false,
      "isAffiliate": false,
      "isOverage": false,
      "isUnderage": false,
      "isReleased": false,
      "seasonId": "2025-26",
      "officeId": 5832,
      "externalId": "1f08270e-e733-66d2-b5b2-06d853421783",
      "id": 2104648,
      "participant": {
        "firstName": "ELIOTT",
        "lastName": "WHITTOM",
        "alternateName": null,
        "pictureUrl": "https://cdn.hcr.spordle.com/members/1ebb64ee-5a17-60f2-8176-021e976b8d94/profile/small/1f0be444-ce88-69ba-870a-067f8c035ee7.jpg",
        "externalId": "1ebb64ee-5a17-60f2-8176-021e976b8d94",
        "id": 955008,
        "fullName": "ELIOTT WHITTOM"
      }
    },
    {
      "teamId": 128312,
      "participantId": 955010,
      "positions": [
        "D"
      ],
      "number": 91,
      "isCaptain": false,
      "isAlternate": false,
      "isAffiliate": false,
      "isOverage": false,
      "isUnderage": false,
      "isReleased": false,
      "seasonId": "2025-26",
      "officeId": 5832,
      "externalId": "1f08270e-eedf-694e-ae9c-06d853421783",
      "id": 2104649,
      "participant": {
        "firstName": "LOUIS-ALEXANDRE",
        "lastName": "CYR",
        "alternateName": null,
        "pictureUrl": "https://cdn.hcr.spordle.com/members/1ebb6591-bdb6-6b46-be92-021e976b8d94/profile/small/1f0be439-acf5-6d6c-b5eb-067f8c035ee7.jpg",
        "externalId": "1ebb6591-bdb6-6b46-be92-021e976b8d94",
        "id": 955010,
        "fullName": "LOUIS-ALEXANDRE CYR"
      }
    },
    {
      "teamId": 128312,
      "participantId": 955012,
      "positions": [
        "G"
      ],
      "number": 70,
      "isCaptain": false,
      "isAlternate": false,
      "isAffiliate": false,
      "isOverage": false,
      "isUnderage": false,
      "isReleased": false,
      "seasonId": "2025-26",
      "officeId": 5832,
      "externalId": "1f08270e-f38b-65ce-aad5-06d853421783",
      "id": 2104650,
      "participant": {
        "firstName": "OLIVIER",
        "lastName": "PELLETIER",
        "alternateName": null,
        "pictureUrl": "https://cdn.hcr.spordle.com/members/1ebb64e0-30d1-6228-9e8d-021e976b8d94/profile/small/1f0be442-fa50-6afe-a872-02ec0d6aa587.jpg",
        "externalId": "1ebb64e0-30d1-6228-9e8d-021e976b8d94",
        "id": 955012,
        "fullName": "OLIVIER PELLETIER"
      }
    },
    {
      "teamId": 128312,
      "participantId": 955011,
      "positions": [
        "D"
      ],
      "number": 21,
      "isCaptain": false,
      "isAlternate": false,
      "isAffiliate": false,
      "isOverage": false,
      "isUnderage": false,
      "isReleased": false,
      "seasonId": "2025-26",
      "officeId": 5832,
      "externalId": "1f08270e-f069-6f12-a72f-06d853421783",
      "id": 2104651,
      "participant": {
        "firstName": "DYLAN",
        "lastName": "OUELLET",
        "alternateName": null,
        "pictureUrl": "https://cdn.hcr.spordle.com/members/1ebb64e2-1a74-6596-909e-021e976b8d94/profile/small/1f0be442-2997-6d9a-8dfa-02ec0d6aa587.jpg",
        "externalId": "1ebb64e2-1a74-6596-909e-021e976b8d94",
        "id": 955011,
        "fullName": "DYLAN OUELLET"
      }
    },
    {
      "teamId": 128312,
      "participantId": 955014,
      "positions": [
        "D"
      ],
      "number": 24,
      "isCaptain": false,
      "isAlternate": false,
      "isAffiliate": false,
      "isOverage": false,
      "isUnderage": false,
      "isReleased": false,
      "seasonId": "2025-26",
      "officeId": 5832,
      "externalId": "1f08270e-ed52-6496-91bb-06d853421783",
      "id": 2104652,
      "participant": {
        "firstName": "ZACH-ALEXANDRE",
        "lastName": "CLAVET",
        "alternateName": null,
        "pictureUrl": null,
        "externalId": "1ebb64e2-5a50-6106-a9e3-021e976b8d94",
        "id": 955014,
        "fullName": "ZACH-ALEXANDRE CLAVET"
      }
    },
    {
      "teamId": 128312,
      "participantId": 955013,
      "positions": [
        "D"
      ],
      "number": 16,
      "isCaptain": false,
      "isAlternate": false,
      "isAffiliate": false,
      "isOverage": false,
      "isUnderage": false,
      "isReleased": false,
      "seasonId": "2025-26",
      "officeId": 5832,
      "externalId": "1f08270e-f1f6-62d6-adb0-06d853421783",
      "id": 2104653,
      "participant": {
        "firstName": "FELIX",
        "lastName": "BOUCHARD",
        "alternateName": null,
        "pictureUrl": "https://cdn.hcr.spordle.com/members/1ebb64e1-c29c-69e0-9cc0-0695742fcc0e/profile/small/1f0be435-75dc-68b6-8a0e-02d85374e4dd.jpg",
        "externalId": "1ebb64e1-c29c-69e0-9cc0-0695742fcc0e",
        "id": 955013,
        "fullName": "FELIX BOUCHARD"
      }
    },
    {
      "teamId": 128312,
      "participantId": 956002,
      "positions": [
        "F"
      ],
      "number": 9,
      "isCaptain": false,
      "isAlternate": false,
      "isAffiliate": false,
      "isOverage": false,
      "isUnderage": false,
      "isReleased": false,
      "seasonId": "2025-26",
      "officeId": 5832,
      "externalId": "1f0840b8-9697-63e0-a881-06d853421783",
      "id": 2109814,
      "participant": {
        "firstName": "LOGAN",
        "lastName": "BLAIS",
        "alternateName": null,
        "pictureUrl": "https://cdn.hcr.spordle.com/members/1ebb6591-dee5-6056-8ddf-06798f358960/profile/small/1f0be434-74e5-6292-969a-02ec0d6aa587.jpg",
        "externalId": "1ebb6591-dee5-6056-8ddf-06798f358960",
        "id": 956002,
        "fullName": "LOGAN BLAIS"
      }
    },
    {
      "teamId": 128312,
      "participantId": 956396,
      "positions": [
        "G"
      ],
      "number": 30,
      "isCaptain": false,
      "isAlternate": false,
      "isAffiliate": false,
      "isOverage": false,
      "isUnderage": false,
      "isReleased": false,
      "seasonId": "2025-26",
      "officeId": 5832,
      "externalId": "1f08462c-11fd-63e0-b95c-06d853421783",
      "id": 2111577,
      "participant": {
        "firstName": "ÉTIENNE",
        "lastName": "GAGNÉ",
        "alternateName": null,
        "pictureUrl": null,
        "externalId": "1ebb64e1-819a-6eb0-bec4-021e976b8d94",
        "id": 956396,
        "fullName": "ÉTIENNE GAGNÉ"
      }
    },
    {
      "teamId": 128312,
      "participantId": 814081,
      "positions": [
        "F"
      ],
      "number": 95,
      "isCaptain": false,
      "isAlternate": false,
      "isAffiliate": false,
      "isOverage": false,
      "isUnderage": false,
      "isReleased": false,
      "seasonId": "2025-26",
      "officeId": 5832,
      "externalId": "1f088381-cf86-6f96-b36e-06d853421783",
      "id": 2117580,
      "participant": {
        "firstName": "JEAN-ALEXY",
        "lastName": "MCINNIS",
        "alternateName": null,
        "pictureUrl": null,
        "externalId": "1ebb6591-1fb5-6820-9266-021e976b8d94",
        "id": 814081,
        "fullName": "JEAN-ALEXY MCINNIS"
      }
    },
    {
      "teamId": 128312,
      "participantId": 963415,
      "positions": [
        "Assistant Coach"
      ],
      "number": null,
      "isCaptain": false,
      "isAlternate": false,
      "isAffiliate": false,
      "isOverage": false,
      "isUnderage": false,
      "isReleased": false,
      "seasonId": "2025-26",
      "officeId": 5832,
      "externalId": "1f08e9ea-3d02-61f0-96f3-028667cee5ff",
      "id": 2139445,
      "participant": {
        "firstName": "ALEX",
        "lastName": "ARSENAULT",
        "alternateName": null,
        "pictureUrl": "https://cdn.hcr.spordle.com/members/1ebb64ed-b4f6-6f3c-b589-021e976b8d94/profile/small/1f0be46f-d076-644a-8920-067f8c035ee7.jpg",
        "externalId": "1ebb64ed-b4f6-6f3c-b589-021e976b8d94",
        "id": 963415,
        "fullName": "ALEX ARSENAULT"
      }
    },
    {
      "teamId": 128312,
      "participantId": 814538,
      "positions": [
        "Assistant Coach"
      ],
      "number": null,
      "isCaptain": false,
      "isAlternate": false,
      "isAffiliate": false,
      "isOverage": false,
      "isUnderage": false,
      "isReleased": false,
      "seasonId": "2025-26",
      "officeId": 5832,
      "externalId": "1f090032-c913-612c-9a9b-026d5f4e9419",
      "id": 2144183,
      "participant": {
        "firstName": "KEVIN-JEFFREY",
        "lastName": "ATCHIRIKI",
        "alternateName": null,
        "pictureUrl": null,
        "externalId": "1ebbf4ac-37cc-6c1a-8557-06bcf2785b72",
        "id": 814538,
        "fullName": "KEVIN-JEFFREY ATCHIRIKI"
      }
    },
    {
      "teamId": 128312,
      "participantId": 964921,
      "positions": [
        "Head Coach"
      ],
      "number": null,
      "isCaptain": false,
      "isAlternate": false,
      "isAffiliate": false,
      "isOverage": false,
      "isUnderage": false,
      "isReleased": false,
      "seasonId": "2025-26",
      "officeId": 5832,
      "externalId": "1f09015f-3df9-6c66-b89b-028667cee5ff",
      "id": 2144673,
      "participant": {
        "firstName": "PHILIPPE",
        "lastName": "LABRIE",
        "alternateName": null,
        "pictureUrl": "https://cdn.hcr.spordle.com/members/1ebbf4a2-8005-6702-960a-0602538cfaba/profile/small/1f0be436-2d61-6f0e-acdc-02ec0d6aa587.jpg",
        "externalId": "1ebbf4a2-8005-6702-960a-0602538cfaba",
        "id": 964921,
        "fullName": "PHILIPPE LABRIE"
      }
    },
    {
      "teamId": 128312,
      "participantId": 954423,
      "positions": [
        "F"
      ],
      "number": 0,
      "isCaptain": false,
      "isAlternate": false,
      "isAffiliate": true,
      "isOverage": false,
      "isUnderage": false,
      "isReleased": false,
      "seasonId": "2025-26",
      "officeId": 5832,
      "externalId": "1f098995-0572-6924-86bb-02c4da980a79",
      "id": 2189468,
      "participant": {
        "firstName": "NAYA",
        "lastName": "BELIVEAU",
        "alternateName": null,
        "pictureUrl": "https://cdn.hcr.spordle.com/members/1ebb64e1-e0b9-6b44-8606-0695742fcc0e/profile/small/1f0be4a1-4129-660c-aa23-02ec0d6aa587.jpg",
        "externalId": "1ebb64e1-e0b9-6b44-8606-0695742fcc0e",
        "id": 954423,
        "fullName": "NAYA BELIVEAU"
      }
    },
    {
      "teamId": 128312,
      "participantId": 954419,
      "positions": [
        "F"
      ],
      "number": 0,
      "isCaptain": false,
      "isAlternate": false,
      "isAffiliate": true,
      "isOverage": false,
      "isUnderage": false,
      "isReleased": false,
      "seasonId": "2025-26",
      "officeId": 5832,
      "externalId": "1f098995-06f7-6f10-a689-02c4da980a79",
      "id": 2189469,
      "participant": {
        "firstName": "JORDAN",
        "lastName": "MURRAY",
        "alternateName": null,
        "pictureUrl": null,
        "externalId": "1ec09752-bacf-6cf0-9c3b-02a13eb7aae4",
        "id": 954419,
        "fullName": "JORDAN MURRAY"
      }
    },
    {
      "teamId": 128312,
      "participantId": 972676,
      "positions": [
        "G"
      ],
      "number": 0,
      "isCaptain": false,
      "isAlternate": false,
      "isAffiliate": true,
      "isOverage": false,
      "isUnderage": false,
      "isReleased": false,
      "seasonId": "2025-26",
      "officeId": 5832,
      "externalId": "1f098995-0882-6b96-bcd7-02c4da980a79",
      "id": 2189470,
      "participant": {
        "firstName": "ANTOINE",
        "lastName": "FRANCOEUR",
        "alternateName": null,
        "pictureUrl": null,
        "externalId": "1ebb64e2-2689-6bd8-9668-0695742fcc0e",
        "id": 972676,
        "fullName": "ANTOINE FRANCOEUR"
      }
    },
    {
      "teamId": 128312,
      "participantId": 954422,
      "positions": [
        "F"
      ],
      "number": 0,
      "isCaptain": false,
      "isAlternate": false,
      "isAffiliate": true,
      "isOverage": false,
      "isUnderage": false,
      "isReleased": false,
      "seasonId": "2025-26",
      "officeId": 5832,
      "externalId": "1f098996-1605-6132-80f2-02c4da980a79",
      "id": 2189481,
      "participant": {
        "firstName": "THEO",
        "lastName": "DIONNE",
        "alternateName": null,
        "pictureUrl": "https://cdn.hcr.spordle.com/members/1ebb64e1-f00e-684c-8b1a-020a2d3ab872/profile/small/1f0be4a3-d779-60ba-830f-067f8c035ee7.jpg",
        "externalId": "1ebb64e1-f00e-684c-8b1a-020a2d3ab872",
        "id": 954422,
        "fullName": "THEO DIONNE"
      }
    },
    {
      "teamId": 128312,
      "participantId": 752938,
      "positions": [
        "G"
      ],
      "number": 0,
      "isCaptain": false,
      "isAlternate": false,
      "isAffiliate": true,
      "isOverage": false,
      "isUnderage": false,
      "isReleased": false,
      "seasonId": "2025-26",
      "officeId": 5832,
      "externalId": "1f0af52e-dde8-68e8-87f2-067f8c035ee7",
      "id": 2455521,
      "participant": {
        "firstName": "LIAM",
        "lastName": "CARON",
        "alternateName": null,
        "pictureUrl": null,
        "externalId": "1ebb64e1-ff05-6b16-93ef-0695742fcc0e",
        "id": 752938,
        "fullName": "LIAM CARON"
      }
    },
    {
      "teamId": 128312,
      "participantId": 980677,
      "positions": [
        "C"
      ],
      "number": 0,
      "isCaptain": false,
      "isAlternate": false,
      "isAffiliate": true,
      "isOverage": false,
      "isUnderage": false,
      "isReleased": false,
      "seasonId": "2025-26",
      "officeId": 5832,
      "externalId": "1f0af52f-91f0-6df4-a0d7-02d85374e4dd",
      "id": 2455523,
      "participant": {
        "firstName": "FRANCOIS-XAVIER",
        "lastName": "BOUCHARD",
        "alternateName": null,
        "pictureUrl": null,
        "externalId": "1ebb64ee-8964-6918-9876-021e976b8d94",
        "id": 980677,
        "fullName": "FRANCOIS-XAVIER BOUCHARD"
      }
    },
    {
      "teamId": 128312,
      "participantId": 814444,
      "positions": [
        "F"
      ],
      "number": 0,
      "isCaptain": false,
      "isAlternate": false,
      "isAffiliate": true,
      "isOverage": false,
      "isUnderage": false,
      "isReleased": false,
      "seasonId": "2025-26",
      "officeId": 5832,
      "externalId": "1f0ee288-8954-6e76-9e43-062edbfc8345",
      "id": 2817874,
      "participant": {
        "firstName": "MAREK",
        "lastName": "DUMAS",
        "alternateName": null,
        "pictureUrl": null,
        "externalId": "1ebb64e1-5691-6426-88c3-0695742fcc0e",
        "id": 814444,
        "fullName": "MAREK DUMAS"
      }
    },
    {
      "teamId": 128312,
      "participantId": 965818,
      "positions": [
        "F"
      ],
      "number": 0,
      "isCaptain": false,
      "isAlternate": false,
      "isAffiliate": true,
      "isOverage": false,
      "isUnderage": false,
      "isReleased": false,
      "seasonId": "2025-26",
      "officeId": 5832,
      "externalId": "1f0f0d8e-f8c7-671e-83c7-06db8c506679",
      "id": 2822908,
      "participant": {
        "firstName": "XAVIER",
        "lastName": "LAVOIE",
        "alternateName": null,
        "pictureUrl": null,
        "externalId": "1ebb64e0-7931-6db0-b677-021e976b8d94",
        "id": 965818,
        "fullName": "XAVIER LAVOIE"
      }
    },
    {
      "teamId": 128312,
      "participantId": 814083,
      "positions": [
        "F"
      ],
      "number": 0,
      "isCaptain": false,
      "isAlternate": false,
      "isAffiliate": true,
      "isOverage": false,
      "isUnderage": false,
      "isReleased": false,
      "seasonId": "2025-26",
      "officeId": 5832,
      "externalId": "1f0f2658-98c6-69ea-89cd-02f41b49034d",
      "id": 2829112,
      "participant": {
        "firstName": "VINCENT",
        "lastName": "BOUTIN",
        "alternateName": null,
        "pictureUrl": null,
        "externalId": "1ebb6591-d550-6482-bb4a-021e976b8d94",
        "id": 814083,
        "fullName": "VINCENT BOUTIN"
      }
    },
    {
      "teamId": 128312,
      "participantId": 833236,
      "positions": [
        "F"
      ],
      "number": 0,
      "isCaptain": false,
      "isAlternate": false,
      "isAffiliate": true,
      "isOverage": false,
      "isUnderage": false,
      "isReleased": false,
      "seasonId": "2025-26",
      "officeId": 5832,
      "externalId": "1f0f2658-944d-6512-9a38-02f41b49034d",
      "id": 2829113,
      "participant": {
        "firstName": "NATHAN",
        "lastName": "MARTICOTTE",
        "alternateName": null,
        "pictureUrl": null,
        "externalId": "1ebb64ee-7b63-6d3c-bf69-068fc9a36a40",
        "id": 833236,
        "fullName": "NATHAN MARTICOTTE"
      }
    },
    {
      "teamId": 128312,
      "participantId": 1025519,
      "positions": [
        "C"
      ],
      "number": 0,
      "isCaptain": false,
      "isAlternate": false,
      "isAffiliate": true,
      "isOverage": false,
      "isUnderage": false,
      "isReleased": false,
      "seasonId": "2025-26",
      "officeId": 5832,
      "externalId": "1f0f2658-96eb-61e8-a26f-02f41b49034d",
      "id": 2829114,
      "participant": {
        "firstName": "THÉO",
        "lastName": "BABIN",
        "alternateName": null,
        "pictureUrl": null,
        "externalId": "1ebb64ee-2b0c-612c-850f-068fc9a36a40",
        "id": 1025519,
        "fullName": "THÉO BABIN"
      }
    },
    {
      "teamId": 128312,
      "participantId": 970284,
      "positions": [
        "C"
      ],
      "number": 0,
      "isCaptain": false,
      "isAlternate": false,
      "isAffiliate": true,
      "isOverage": false,
      "isUnderage": false,
      "isReleased": false,
      "seasonId": "2025-26",
      "officeId": 5832,
      "externalId": "1f0f2658-934a-6e12-be46-02f41b49034d",
      "id": 2829115,
      "participant": {
        "firstName": "ELOI",
        "lastName": "TAPP",
        "alternateName": null,
        "pictureUrl": null,
        "externalId": "1ebb64ee-874e-65b6-b893-020a2d3ab872",
        "id": 970284,
        "fullName": "ELOI TAPP"
      }
    },
    {
      "teamId": 128312,
      "participantId": 999507,
      "positions": [
        "D"
      ],
      "number": 0,
      "isCaptain": false,
      "isAlternate": false,
      "isAffiliate": true,
      "isOverage": false,
      "isUnderage": false,
      "isReleased": false,
      "seasonId": "2025-26",
      "officeId": 5832,
      "externalId": "1f0f2658-9565-6dc8-8c20-02f41b49034d",
      "id": 2829116,
      "participant": {
        "firstName": "RÉMI",
        "lastName": "WHITTY",
        "alternateName": null,
        "pictureUrl": null,
        "externalId": "1ebb64ee-84d8-603e-b9b3-020a2d3ab872",
        "id": 999507,
        "fullName": "RÉMI WHITTY"
      }
    }
  ],
  "gamesheet_pdf_file": "web/data/gamesheets/game_625444.pdf",
  "starting_goalies": {
    "home_goalie": "OLIVIER PELLETIER",
    "away_goalie": "JEAN-PHILIPPE GILBERT"
  }
}